pychatbot2/__init__.py
pychatbot2/client.py
pychatbot2/db.py
pychatbot2/types.py
pychatbot2-0.1.6.dist-info/METADATA
pychatbot2-0.1.6.dist-info/WHEEL
pychatbot2-0.1.6.dist-info/RECORD
