Metadata-Version: 2.4
Name: pychatbot2
Version: 0.1.6
Summary: Python client for chatbot platform
Project-URL: Homepage, https://github.com/yourusername/pychatbot2
Project-URL: Repository, https://github.com/yourusername/pychatbot2.git
Author-email: dada <dada@example.com>
License-Expression: MIT
Keywords: chatbot,python,sdk
Classifier: Development Status :: 3 - Alpha
Classifier: Intended Audience :: Developers
Classifier: License :: OSI Approved :: MIT License
Classifier: Programming Language :: Python :: 3
Classifier: Programming Language :: Python :: 3.8
Classifier: Programming Language :: Python :: 3.9
Classifier: Programming Language :: Python :: 3.10
Classifier: Programming Language :: Python :: 3.11
Requires-Python: >=3.8
Requires-Dist: aiohttp-sse-client>=0.2.1
Requires-Dist: aiohttp>=3.8.0
